rg3py/__init__.py
rg3py/rg3py.pyi
rg3py/rg3py.so
rg3py-0.0.24.dist-info/METADATA
rg3py-0.0.24.dist-info/WHEEL
rg3py-0.0.24.dist-info/top_level.txt
rg3py-0.0.24.dist-info/RECORD
